{
  "stop_state": "5e14ef57326c1096d18ebdcce21db29e", 
  "event_str": "TouchEvent", 
  "tag": "2021-11-03_190340", 
  "event": {
    "y": null, 
    "x": null, 
    "view": {
      "content_description": null, 
      "resource_id": null, 
      "text": null, 
      "editable": false, 
      "visible": true, 
      "is_password": false, 
      "focused": false, 
      "clickable": true, 
      "checkable": false, 
      "size": "428*84", 
      "scrollable": false, 
      "checked": false, 
      "package": "me.zhanghai.android.files", 
      "long_clickable": false, 
      "selected": false, 
      "enabled": true, 
      "bounds": [
        [
          292, 
          412
        ], 
        [
          720, 
          496
        ]
      ], 
      "class": "android.widget.LinearLayout", 
      "focusable": false
    }, 
    "id": 4, 
    "event_type": "touch"
  }, 
  "start_state": "1db2000682987760cb970f2fadbc6658"
}